edualgo/BinaryTree.py
edualgo/LinkedList.py
edualgo/__init__.py
edualgo/algorithms.py
edualgo/queue.py
edualgo/stack.py
eduAlgo-1.2.1.4.dist-info/LICENSE.txt
eduAlgo-1.2.1.4.dist-info/METADATA
eduAlgo-1.2.1.4.dist-info/WHEEL
eduAlgo-1.2.1.4.dist-info/top_level.txt
eduAlgo-1.2.1.4.dist-info/RECORD
