Metadata-Version: 2.1
Name: eduAlgo
Version: 1.2.1.4
Summary: An educational software to make Algorithm learning & implementation easier in python
Home-page: https://github.com/edualgo/eduAlgo
Author: Abhijit Tripathy
Author-email: founder@edualgoacademy.com
License: MIT
Keywords: algorithms
Platform: UNKNOWN
Classifier: Development Status :: 5 - Production/Stable
Classifier: Intended Audience :: Developers
Classifier: Topic :: Software Development
Classifier: License :: OSI Approved :: MIT License
Classifier: Programming Language :: Python :: 3.8
Requires-Dist: requests
Requires-Dist: tabulate
